<?xml version = '1.0' encoding = 'UTF-8'?>
<TableProxyOraclev20c class="oracle.dbtools.crest.model.design.storage.oracle.v20c.TableProxyOraclev20c" name="MOVIMIENTO_CAJA" directorySegmentName="seg_0" id="56979F9A-293F-EF10-9BF3-4F6EBBA052C4">
<createdBy>daemu</createdBy>
<createdTime>2026-06-04 18:11:53 UTC</createdTime>
<ownerDesignName>SIVEBO</ownerDesignName>
<partitionedRowMovement>DISABLE</partitionedRowMovement>
<temporaryChanged>false</temporaryChanged>
<accessDriverType>oracle_loader</accessDriverType>
<rejectLimit></rejectLimit>
<columnProxies itemClass="oracle.dbtools.crest.model.design.storage.oracle.v12c.ColumnProxyOraclev12c">
<ColumnProxy name="monto" id="23838058-21EC-8F59-109A-690AA883F3EC">
<createdBy>daemu</createdBy>
<createdTime>2026-06-04 18:11:53 UTC</createdTime>
<ownerDesignName>SIVEBO</ownerDesignName>
</ColumnProxy>
<ColumnProxy name="id_mov" id="39B072BC-DD18-CA8F-5899-C0362F6EF65D">
<createdBy>daemu</createdBy>
<createdTime>2026-06-04 18:11:53 UTC</createdTime>
<ownerDesignName>SIVEBO</ownerDesignName>
<autoIncrementDDL>DEFAULT_CLAUSE</autoIncrementDDL>
<defaultValue>seq_movimiento_caja.NEXTVAL</defaultValue>
</ColumnProxy>
<ColumnProxy name="tipo" id="3E516DE7-F48D-1F9A-4585-38FE95A7BB66">
<createdBy>daemu</createdBy>
<createdTime>2026-06-04 18:11:53 UTC</createdTime>
<ownerDesignName>SIVEBO</ownerDesignName>
</ColumnProxy>
<ColumnProxy name="concepto" id="D370E19E-8461-F582-6E3B-C2EFF2B556F8">
<createdBy>daemu</createdBy>
<createdTime>2026-06-04 18:11:53 UTC</createdTime>
<ownerDesignName>SIVEBO</ownerDesignName>
</ColumnProxy>
<ColumnProxy name="id_venta" id="E0D2145D-062C-1C13-CD37-3D2317204D45">
<createdBy>daemu</createdBy>
<createdTime>2026-06-04 18:11:53 UTC</createdTime>
<ownerDesignName>SIVEBO</ownerDesignName>
</ColumnProxy>
<ColumnProxy name="id_sesion" id="F350B927-9004-4CDE-DD85-B2C9943EDECF">
<createdBy>daemu</createdBy>
<createdTime>2026-06-04 18:11:53 UTC</createdTime>
<ownerDesignName>SIVEBO</ownerDesignName>
</ColumnProxy>
</columnProxies>
<indexProxies>
<IndexProxy class="oracle.dbtools.crest.model.design.storage.oracle.v10g.IndexProxyOraclev10g" name="idx_mov_venta" id="5533ACC3-A1C5-5ED8-C395-C5F666CB2507">
<createdBy>daemu</createdBy>
<createdTime>2026-06-04 18:11:53 UTC</createdTime>
<ownerDesignName>SIVEBO</ownerDesignName>
<logging></logging>
</IndexProxy>
<IndexProxy class="oracle.dbtools.crest.model.design.storage.oracle.v10g.IndexProxyOraclev10g" name="idx_mov_sesion" id="94B7F3B7-FF2D-7B28-FCF4-14AE291A3BE7">
<createdBy>daemu</createdBy>
<createdTime>2026-06-04 18:11:53 UTC</createdTime>
<ownerDesignName>SIVEBO</ownerDesignName>
<logging></logging>
</IndexProxy>
</indexProxies>
<foreignKeys>
<ForeignKey class="oracle.dbtools.crest.model.design.storage.oracle.v10g.FKProxyOraclev10g" name="fk_movimiento_caja_venta" id="78018FBE-4885-3DD7-D87B-00E246AEC32E">
<createdBy>daemu</createdBy>
<createdTime>2026-06-04 18:11:53 UTC</createdTime>
<ownerDesignName>SIVEBO</ownerDesignName>
</ForeignKey>
<ForeignKey class="oracle.dbtools.crest.model.design.storage.oracle.v10g.FKProxyOraclev10g" name="fk_movimiento_caja_sesion" id="79C5F6AA-FD27-D7E1-98FE-4B27F9CB9CBB">
<createdBy>daemu</createdBy>
<createdTime>2026-06-04 18:11:53 UTC</createdTime>
<ownerDesignName>SIVEBO</ownerDesignName>
</ForeignKey>
</foreignKeys>
<primaryKeys>
<PrimaryKey class="oracle.dbtools.crest.model.design.storage.oracle.v10g.PKProxyOraclev10g" name="pk_movimiento_caja" id="B515BEC2-DD77-BE65-3D2F-242A88E8271D">
<createdBy>daemu</createdBy>
<createdTime>2026-06-04 18:11:53 UTC</createdTime>
<ownerDesignName>SIVEBO</ownerDesignName>
<indexSort>SORTED</indexSort>
</PrimaryKey>
</primaryKeys>
<tableCheckConstraints itemClass="oracle.dbtools.crest.model.design.storage.oracle.TableCheckConstraintOracle">
<TableCheckConstraint name="ck_movimiento_caja_tipo" id="0E2F7E1B-401B-1107-A764-28F4AC16CE50">
<createdBy>daemu</createdBy>
<createdTime>2026-06-04 18:11:53 UTC</createdTime>
<ownerDesignName>SIVEBO</ownerDesignName>
</TableCheckConstraint>
<TableCheckConstraint name="ck_movimiento_caja_monto" id="62D164C6-08E5-CDFC-1E6E-33D19A5EF397">
<createdBy>daemu</createdBy>
<createdTime>2026-06-04 18:11:53 UTC</createdTime>
<ownerDesignName>SIVEBO</ownerDesignName>
</TableCheckConstraint>
</tableCheckConstraints>
</TableProxyOraclev20c>